porngen/__init__.py
porngen/porngen.py
porngen-1.0.0.dist-info/LICENSE
porngen-1.0.0.dist-info/METADATA
porngen-1.0.0.dist-info/WHEEL
porngen-1.0.0.dist-info/top_level.txt
porngen-1.0.0.dist-info/RECORD
