Metadata-Version: 2.1
Name: porngen
Version: 1.0.0
Summary: Porn content search module.
Home-page: https://github.com/DedInc/porngen
Author: Maehdakvan
Author-email: visitanimation@google.com
License: UNKNOWN
Project-URL: Bug Tracker, https://github.com/DedInc/porngen/issues
Platform: UNKNOWN
Classifier: Programming Language :: Python :: 3
Classifier: License :: OSI Approved :: MIT License
Classifier: Operating System :: OS Independent
Requires-Python: >=3.6
License-File: LICENSE
Requires-Dist: requests
Requires-Dist: requests-html
Requires-Dist: lxml
